dseo/__init__.py
dseo/admin.py
dseo/apps.py
dseo/models.py
dseo/translation.py
dseo/urls.py
dseo/utils.py
dseo/views.py
dseo/migrations/0001_initial.py
dseo/migrations/0002_auto_20180716_1030.py
dseo/migrations/0002_auto_20180716_1050.py
dseo/migrations/0003_merge_20180716_1131.py
dseo/migrations/0004_auto_20180718_1004.py
dseo/migrations/__init__.py
dseo/templates/templatetags/data.html
dseo/templates/templatetags/meta.html
dseo/templatetags/__init__.py
dseo/templatetags/dseo_tags.py
dseo-0.1.dev0.dist-info/LICENSE.txt
dseo-0.1.dev0.dist-info/METADATA
dseo-0.1.dev0.dist-info/WHEEL
dseo-0.1.dev0.dist-info/top_level.txt
dseo-0.1.dev0.dist-info/RECORD
