Metadata-Version: 2.1
Name: dseo
Version: 0.1.dev0
Summary: Django module for metadata
Home-page: UNKNOWN
Author: Mikhail Andreev
Author-email: datysho@gmail.com
License: BSD
Platform: UNKNOWN
Classifier: Programming Language :: Python :: 3
Classifier: Operating System :: OS Independent
